README.md
setup.cfg
setup.py
torchsenti/__init__.py
torchsenti.egg-info/PKG-INFO
torchsenti.egg-info/SOURCES.txt
torchsenti.egg-info/dependency_links.txt
torchsenti.egg-info/requires.txt
torchsenti.egg-info/top_level.txt
torchsenti/datasets/__init__.py
torchsenti/datasets/city_search.py
torchsenti/datasets/imdb.py
torchsenti/datasets/movie_review.py
torchsenti/datasets/pros_and_cons.py
torchsenti/datasets/trip_advisor.py
torchsenti/datasets/utils.py
torchsenti/datasets/yelp_review.py
torchsenti/models/__init__.py